examples/__init__.py
examples/duplicate_aliases.py
examples/flag_and_option_specifications.py
examples/multiple_options.py
examples/sections.py
examples/show_usage_and_version.py
examples/test_usage.py
examples/typed_options.py
pyclasp/__init__.py
pyclasp/arguments.py
pyclasp/cli.py
pyclasp/exceptions.py
pyclasp/flag_argument.py
pyclasp/flag_specification.py
pyclasp/option_argument.py
pyclasp/option_specification.py
pyclasp/section_specification.py
pyclasp/specification.py
pyclasp/util.py
tests/__init__.py
tests/test_arguments.py
tests/test_cli.py
tests/test_options.py
tests/test_sections.py
tests/test_typed_values.py
pyclasp-0.8.9.dist-info/LICENSE
pyclasp-0.8.9.dist-info/METADATA
pyclasp-0.8.9.dist-info/WHEEL
pyclasp-0.8.9.dist-info/top_level.txt
pyclasp-0.8.9.dist-info/RECORD
