Metadata-Version: 2.1
Name: pyclasp
Version: 0.8.9
Summary: Command-Line Argument Sorting and Parsing, for Python
Home-page: https://github.com/synesissoftware/clasp.Python
Author: Matt Wilson
Author-email: matthew@synesis.com.au
License: BSD-3-Clause
Keywords: Command-line CLI parsing
Classifier: Intended Audience :: Developers
Classifier: License :: OSI Approved :: BSD License
Classifier: Natural Language :: English
Classifier: Operating System :: OS Independent
Classifier: Programming Language :: Python
Classifier: Programming Language :: Python :: 2
Classifier: Programming Language :: Python :: 3
License-File: LICENSE
